NumOpt/__init__.py
NumOpt/cprint.py
NumOpt/opti.py
NumOpt/FSI/__init__.py
NumOpt/FSI/tools.py
NumOpt/airfoil/bezier.py
NumOpt/nx/__init__.py
NumOpt/nx/tools.py
NumOpt/optimize/__init__.py
NumOpt/optimize/hxy_optimization.py
NumOpt/preprocess/scaler.py
numopt-0.0.4.dist-info/licenses/LICENSE.txt
numopt-0.0.4.dist-info/METADATA
numopt-0.0.4.dist-info/WHEEL
numopt-0.0.4.dist-info/top_level.txt
numopt-0.0.4.dist-info/RECORD
