Metadata-Version: 2.4
Name: NumOpt
Version: 0.0.4
Summary: pti is a Python package that helps you design and optimize engineered systems.
Home-page: https://github.com/Zcaic/NumOpt.git
Author: Zcaic
License: MIT License
Project-URL: homepage, https://github.com/Zcaic/NumOpt.git
Keywords: optimization,automatic,differentiation
Classifier: Development Status :: 5 - Production/Stable
Classifier: Intended Audience :: Science/Research
Classifier: Topic :: Scientific/Engineering :: Physics
Classifier: License :: OSI Approved :: MIT License
Classifier: Programming Language :: Python :: 3
Requires-Python: >=3.9
License-File: LICENSE.txt
Requires-Dist: aerosandbox>=4.2.8
Requires-Dist: termcolor>=3.1.0
Dynamic: home-page
Dynamic: license-file
Dynamic: requires-python
